src/pe.sv
`timescale 1ns/1ps
`default_nettype none

module pe (
    input logic clk,
    input logic rst,
    input logic start,
    input logic load_weight,
    input logic [15:0] input_in,
    input logic [15:0] psum_in,
    input logic [15:0] weight,
    output logic [15:0] input_out,
    output logic [15:0] psum_out
    );

    logic [15:0] weight_reg;

    always_ff @(posedge clk or posedge rst) begin
        if (rst) begin
            input_out <= 0;
            psum_out <= 0;
            weight_reg <= 0;
        end else if (load_weight) begin
            weight_reg <= weight;
        end else if (start) begin
            input_out <= input_in;
            psum_out <= (input_in * weight_reg) + psum_in;
        end
    end

endmodule

src/systolic.sv
`timescale 1ns/1ps
`default_nettype none


// 3x3 systolic array
module systolic (
    input logic clk,
    input logic rst,
    input logic start,
    input logic load_weights,
    input logic [15:0] input_11,
    input logic [15:0] input_21,
    input logic [15:0] input_31,
    input logic [15:0] weight_11,
    input logic [15:0] weight_12,
    input logic [15:0] weight_13,
    input logic [15:0] weight_21,
    input logic [15:0] weight_22,
    input logic [15:0] weight_23,
    input logic [15:0] weight_31,
    input logic [15:0] weight_32,
    input logic [15:0] weight_33,
    output logic [15:0] out_31,
    output logic [15:0] out_32,
    output logic [15:0] out_33,
    output logic done
);

    // input_out for each PE
    logic [15:0] input_11_out;
    logic [15:0] input_12_out;
    logic [15:0] input_21_out;
    logic [15:0] input_22_out;
    logic [15:0] input_31_out;
    logic [15:0] input_32_out;

    // psum_out for each PE
    logic [15:0] psum_11;
    logic [15:0] psum_12;
    logic [15:0] psum_13;
    logic [15:0] psum_21;
    logic [15:0] psum_22;
    logic [15:0] psum_23;

    logic [15:0] zero_wire;
    assign zero_wire = 16'b0;

    pe pe11 (
        .clk(clk),
        .rst(rst),
        .start(start),
        .input_in(input_11),
        .psum_in(zero_wire),
        .weight(weight_11),
        .load_weight(load_weights),
        .input_out(input_11_out),
        .psum_out(psum_11)
    );

    pe pe12 (
        .clk(clk),
        .rst(rst),
        .start(start),
        .input_in(input_11_out),
        .psum_in(zero_wire),
        .weight(weight_12),
        .load_weight(load_weights),
        .input_out(input_12_out),
        .psum_out(psum_12)
    );

    pe pe13 (
        .clk(clk),
        .rst(rst),
        .start(start),
        .input_in(input_12_out),
        .psum_in(zero_wire),
        .weight(weight_13),
        .load_weight(load_weights),
        .input_out(),
        .psum_out(psum_13)
    );

    pe pe21 (
        .clk(clk),
        .rst(rst),
        .start(start),
        .input_in(input_21),
        .psum_in(psum_11),
        .weight(weight_21),
        .load_weight(load_weights),
        .input_out(input_21_out),
        .psum_out(psum_21)
    );

    pe pe22 (
        .clk(clk),
        .rst(rst),
        .start(start),
        .input_in(input_21_out),
        .psum_in(psum_12),
        .weight(weight_22),
        .load_weight(load_weights),
        .input_out(input_22_out),
        .psum_out(psum_22)
    );

    pe pe23 (
        .clk(clk),
        .rst(rst),
        .start(start),
        .input_in(input_22_out),
        .psum_in(psum_13),
        .weight(weight_23),
        .load_weight(load_weights),
        .input_out(),  
        .psum_out(psum_23)
    );

    pe pe31 (
        .clk(clk),
        .rst(rst),
        .start(start),
        .input_in(input_31),
        .psum_in(psum_21),
        .weight(weight_31),
        .load_weight(load_weights),
        .input_out(input_31_out),
        .psum_out(out_31)
    );

    pe pe32 (
        .clk(clk),
        .rst(rst),
        .start(start),
        .input_in(input_31_out),
        .psum_in(psum_22),
        .weight(weight_32),
        .load_weight(load_weights),
        .input_out(input_32_out),
        .psum_out(out_32)
    );

    pe pe33 (
        .clk(clk),
        .rst(rst),
        .start(start),
        .input_in(input_32_out),
        .psum_in(psum_23),
        .weight(weight_33),
        .load_weight(load_weights),
        .input_out(),
        .psum_out(out_33)
    );

endmodule

waveforms/systolic.vcd
$date
	Sun May 18 12:22:21 2025
$end
$version
	Icarus Verilog
$end
$timescale
	1ps
$end
$scope module systolic $end
$var wire 1 ! clk $end
$var wire 16 " input_11 [15:0] $end
$var wire 16 # input_21 [15:0] $end
$var wire 16 $ input_31 [15:0] $end
$var wire 1 % load_weights $end
$var wire 1 & rst $end
$var wire 1 ' start $end
$var wire 16 ( weight_11 [15:0] $end
$var wire 16 ) weight_12 [15:0] $end
$var wire 16 * weight_13 [15:0] $end
$var wire 16 + weight_21 [15:0] $end
$var wire 16 , weight_22 [15:0] $end
$var wire 16 - weight_23 [15:0] $end
$var wire 16 . weight_31 [15:0] $end
$var wire 16 / weight_32 [15:0] $end
$var wire 16 0 weight_33 [15:0] $end
$var wire 16 1 zero_wire [15:0] $end
$var wire 16 2 psum_23 [15:0] $end
$var wire 16 3 psum_22 [15:0] $end
$var wire 16 4 psum_21 [15:0] $end
$var wire 16 5 psum_13 [15:0] $end
$var wire 16 6 psum_12 [15:0] $end
$var wire 16 7 psum_11 [15:0] $end
$var wire 16 8 out_33 [15:0] $end
$var wire 16 9 out_32 [15:0] $end
$var wire 16 : out_31 [15:0] $end
$var wire 16 ; input_32_out [15:0] $end
$var wire 16 < input_31_out [15:0] $end
$var wire 16 = input_22_out [15:0] $end
$var wire 16 > input_21_out [15:0] $end
$var wire 16 ? input_12_out [15:0] $end
$var wire 16 @ input_11_out [15:0] $end
$var reg 1 A done $end
$scope module pe11 $end
$var wire 1 ! clk $end
$var wire 16 B input_in [15:0] $end
$var wire 1 % load_weight $end
$var wire 16 C psum_in [15:0] $end
$var wire 1 & rst $end
$var wire 1 ' start $end
$var wire 16 D weight [15:0] $end
$var reg 16 E input_out [15:0] $end
$var reg 16 F psum_out [15:0] $end
$var reg 16 G weight_reg [15:0] $end
$upscope $end
$scope module pe12 $end
$var wire 1 ! clk $end
$var wire 16 H input_in [15:0] $end
$var wire 1 % load_weight $end
$var wire 16 I psum_in [15:0] $end
$var wire 1 & rst $end
$var wire 1 ' start $end
$var wire 16 J weight [15:0] $end
$var reg 16 K input_out [15:0] $end
$var reg 16 L psum_out [15:0] $end
$var reg 16 M weight_reg [15:0] $end
$upscope $end
$scope module pe13 $end
$var wire 1 ! clk $end
$var wire 16 N input_in [15:0] $end
$var wire 1 % load_weight $end
$var wire 16 O psum_in [15:0] $end
$var wire 1 & rst $end
$var wire 1 ' start $end
$var wire 16 P weight [15:0] $end
$var reg 16 Q input_out [15:0] $end
$var reg 16 R psum_out [15:0] $end
$var reg 16 S weight_reg [15:0] $end
$upscope $end
$scope module pe21 $end
$var wire 1 ! clk $end
$var wire 16 T input_in [15:0] $end
$var wire 1 % load_weight $end
$var wire 16 U psum_in [15:0] $end
$var wire 1 & rst $end
$var wire 1 ' start $end
$var wire 16 V weight [15:0] $end
$var reg 16 W input_out [15:0] $end
$var reg 16 X psum_out [15:0] $end
$var reg 16 Y weight_reg [15:0] $end
$upscope $end
$scope module pe22 $end
$var wire 1 ! clk $end
$var wire 16 Z input_in [15:0] $end
$var wire 1 % load_weight $end
$var wire 16 [ psum_in [15:0] $end
$var wire 1 & rst $end
$var wire 1 ' start $end
$var wire 16 \ weight [15:0] $end
$var reg 16 ] input_out [15:0] $end
$var reg 16 ^ psum_out [15:0] $end
$var reg 16 _ weight_reg [15:0] $end
$upscope $end
$scope module pe23 $end
$var wire 1 ! clk $end
$var wire 16 ` input_in [15:0] $end
$var wire 1 % load_weight $end
$var wire 16 a psum_in [15:0] $end
$var wire 1 & rst $end
$var wire 1 ' start $end
$var wire 16 b weight [15:0] $end
$var reg 16 c input_out [15:0] $end
$var reg 16 d psum_out [15:0] $end
$var reg 16 e weight_reg [15:0] $end
$upscope $end
$scope module pe31 $end
$var wire 1 ! clk $end
$var wire 16 f input_in [15:0] $end
$var wire 1 % load_weight $end
$var wire 16 g psum_in [15:0] $end
$var wire 1 & rst $end
$var wire 1 ' start $end
$var wire 16 h weight [15:0] $end
$var reg 16 i input_out [15:0] $end
$var reg 16 j psum_out [15:0] $end
$var reg 16 k weight_reg [15:0] $end
$upscope $end
$scope module pe32 $end
$var wire 1 ! clk $end
$var wire 16 l input_in [15:0] $end
$var wire 1 % load_weight $end
$var wire 16 m psum_in [15:0] $end
$var wire 1 & rst $end
$var wire 1 ' start $end
$var wire 16 n weight [15:0] $end
$var reg 16 o input_out [15:0] $end
$var reg 16 p psum_out [15:0] $end
$var reg 16 q weight_reg [15:0] $end
$upscope $end
$scope module pe33 $end
$var wire 1 ! clk $end
$var wire 16 r input_in [15:0] $end
$var wire 1 % load_weight $end
$var wire 16 s psum_in [15:0] $end
$var wire 1 & rst $end
$var wire 1 ' start $end
$var wire 16 t weight [15:0] $end
$var reg 16 u input_out [15:0] $end
$var reg 16 v psum_out [15:0] $end
$var reg 16 w weight_reg [15:0] $end
$upscope $end
$upscope $end
$enddefinitions $end
$comment Show the parameter values. $end
$dumpall
$end
#0
$dumpvars
b0 w
b0 v
b0 u
b0 t
b0 s
b0 r
b0 q
b0 p
b0 o
b0 n
b0 m
b0 l
b0 k
b0 j
b0 i
b0 h
b0 g
b0 f
b0 e
b0 d
b0 c
b0 b
b0 a
b0 `
b0 _
b0 ^
b0 ]
b0 \
b0 [
b0 Z
b0 Y
b0 X
b0 W
b0 V
b0 U
b0 T
b0 S
b0 R
b0 Q
b0 P
b0 O
b0 N
b0 M
b0 L
b0 K
b0 J
b0 I
b0 H
b0 G
b0 F
b0 E
b0 D
b0 C
b0 B
xA
b0 @
b0 ?
b0 >
b0 =
b0 <
b0 ;
b0 :
b0 9
b0 8
b0 7
b0 6
b0 5
b0 4
b0 3
b0 2
b0 1
b0 0
b0 /
b0 .
b0 -
b0 ,
b0 +
b0 *
b0 )
b0 (
0'
1&
0%
b0 $
b0 #
b0 "
1!
$end
#5000
0!
#10000
1!
0&
#15000
0!
#20000
b1 G
b10 M
b11 S
b100 Y
b101 _
b110 e
b111 k
b1000 q
b1001 w
1!
b1001 0
b1001 t
b1000 /
b1000 n
b111 .
b111 h
b110 -
b110 b
b101 ,
b101 \
b100 +
b100 V
b11 *
b11 P
b10 )
b10 J
b1 (
b1 D
1%
#25000
0!
#30000
1!
0%
1'
#35000
0!
#40000
b101 7
b101 F
b101 U
b101 @
b101 E
b101 H
1!
b101 "
b101 B
#45000
0!
#50000
b11101 4
b11101 X
b11101 g
b110 >
b110 W
b110 Z
b1010 6
b1010 L
b1010 [
b101 ?
b101 K
b101 N
b0 7
b0 F
b0 U
b0 @
b0 E
b0 H
1!
b110 #
b110 T
b0 "
b0 B
#55000
0!
#60000
b0 6
b0 L
b0 [
b0 ?
b0 K
b0 N
b1111 5
b1111 R
b1111 a
b101 Q
b0 4
b0 X
b0 g
b0 >
b0 W
b0 Z
b101000 3
b101000 ^
b101000 m
b110 =
b110 ]
b110 `
b1001110 :
b1001110 j
b111 <
b111 i
b111 l
1!
b111 $
b111 f
b0 #
b0 T
#65000
0!
#70000
b1100000 9
b1100000 p
b111 ;
b111 o
b111 r
b0 :
b0 j
b0 <
b0 i
b0 l
b110011 2
b110011 d
b110011 s
b110 c
b0 3
b0 ^
b0 m
b0 =
b0 ]
b0 `
b0 5
b0 R
b0 a
b0 Q
1!
b0 $
b0 f
#75000
0!
#80000
b0 2
b0 d
b0 s
b0 c
b0 9
b0 p
b0 ;
b0 o
b0 r
b1110010 8
b1110010 v
b111 u
1!
#85000
0!
#90000
b0 8
b0 v
b0 u
1!
